superpaper/__init__.py
superpaper/__main__.py
superpaper/__version__.py
superpaper/cli.py
superpaper/configuration_dialogs.py
superpaper/data.py
superpaper/gui.py
superpaper/message_dialog.py
superpaper/perspective.py
superpaper/sp_logging.py
superpaper/sp_paths.py
superpaper/spanmode.py
superpaper/superpaper.py
superpaper/tray.py
superpaper/wallpaper_processing.py
superpaper/wallpaper_windows.py
superpaper/profiles/example.profile
superpaper/profiles/example_multi.profile
superpaper/resources/icons8-merge-horizontal-96.png
superpaper/resources/icons8-merge-vertical-96.png
superpaper/resources/superpaper.png
superpaper/resources/test.png
superpaper-2.2.1.data/data/share/applications/superpaper.desktop
superpaper-2.2.1.data/data/share/icons/hicolor/256x256/apps/superpaper.png
superpaper-2.2.1.dist-info/LICENSE
superpaper-2.2.1.dist-info/METADATA
superpaper-2.2.1.dist-info/WHEEL
superpaper-2.2.1.dist-info/entry_points.txt
superpaper-2.2.1.dist-info/top_level.txt
superpaper-2.2.1.dist-info/RECORD
