Metadata-Version: 2.1
Name: superpaper
Version: 2.2.1
Summary: Cross-platform wallpaper manager that focuses on multi-monitor support. Features include ppi corrections, keyboard shortcuts, slideshow.
Home-page: https://github.com/hhannine/superpaper
Author: Henri Hänninen
License: MIT
Keywords: dual-monitor multi-monitor wallpaper background manager
Classifier: Development Status :: 5 - Production/Stable
Classifier: Environment :: X11 Applications
Classifier: Intended Audience :: End Users/Desktop
Classifier: License :: OSI Approved :: MIT License
Classifier: Natural Language :: English
Classifier: Operating System :: POSIX :: Linux
Classifier: Programming Language :: Python :: 3.6
Classifier: Topic :: Utilities
License-File: LICENSE
Requires-Dist: Pillow (>=7.0.0)
Requires-Dist: screeninfo (>=0.6.1)
Requires-Dist: numpy (>=1.18.0)
Requires-Dist: system-hotkey310 (>=1.0.5)
Requires-Dist: xcffib (>=0.8.0)
Requires-Dist: xpybutil (>=0.0.5)
